napari_blosc2/__init__.py
napari_blosc2/_reader.py
napari_blosc2/_writer.py
napari_blosc2/napari.yaml
napari_blosc2/_tests/__init__.py
napari_blosc2-0.0.2.dist-info/LICENSE
napari_blosc2-0.0.2.dist-info/METADATA
napari_blosc2-0.0.2.dist-info/WHEEL
napari_blosc2-0.0.2.dist-info/entry_points.txt
napari_blosc2-0.0.2.dist-info/top_level.txt
napari_blosc2-0.0.2.dist-info/RECORD
